routy/Logger.py
routy/__init__.py
routy/comparison.py
routy/main.py
routy-0.1.2.dist-info/METADATA
routy-0.1.2.dist-info/WHEEL
routy-0.1.2.dist-info/top_level.txt
routy-0.1.2.dist-info/RECORD
