Metadata-Version: 2.1
Name: routy
Version: 0.1.2
Summary: Library for comparing routing models
Home-page: https://github.com/sofaki000/routy
Author: Sofia Kardami
Author-email: sofikardami2000@gmail.com
License: MIT
Classifier: Intended Audience :: Developers
Classifier: License :: OSI Approved :: MIT License
Classifier: Programming Language :: Python
Classifier: Programming Language :: Python :: 3
Classifier: Programming Language :: Python :: 3.6
Classifier: Programming Language :: Python :: 3.7
Classifier: Programming Language :: Python :: 3.8
Classifier: Programming Language :: Python :: 3.9
Classifier: Operating System :: OS Independent
Requires-Dist: numpy
